gituptools/__init__.py
gituptools/gitlab.py
gituptools/utils.py
gituptools/static/license.hex.json
gituptools/static/vars.gitlab.txt
gituptools/static/version.regex
gituptools-124.dist-info/METADATA
gituptools-124.dist-info/WHEEL
gituptools-124.dist-info/top_level.txt
gituptools-124.dist-info/zip-safe
gituptools-124.dist-info/RECORD
