Metadata-Version: 2.1
Name: gituptools
Version: 124
Summary: Setuptools helper for packaging Python from Gitlab.
Home-page: https://gitlab.com/sol-courtney/python-packages/gituptools
Download-URL: https://pypi.org/project/gituptools/#files
Author: Sol Courtney
Author-email: sol.courtney@gmail.com
Maintainer: Sol Courtney
Maintainer-email: sol.courtney@gmail.com
License: GNU General Public License v3 (GPLv3)
Project-URL: Documentation, https://gituptools.readthedocs.io
Project-URL: Gitlab Pages, https://sol-courtney.gitlab.io/python-packages/gituptools
Project-URL: Source Code, https://gitlab.com/sol-courtney/python-packages/gituptools
Project-URL: Tracker, https://gitlab.com/sol-courtney/python-packages/gituptools/-/issues
Keywords: Gitlab,DevOps,CICD,Packaging
Platform: Windows
Platform: Linux
Platform: Solaris
Platform: Mac OS-X
Platform: Unix
Classifier: Development Status :: 4 - Beta
Classifier: Topic :: Utilities
Classifier: Topic :: Software Development :: Build Tools
Classifier: Topic :: Software Development :: Libraries
Classifier: Topic :: Software Development :: Libraries :: Python Modules
Classifier: Topic :: System :: Archiving :: Packaging
Classifier: Framework :: Setuptools Plugin
Classifier: Intended Audience :: Developers
Classifier: Intended Audience :: Information Technology
Classifier: License :: OSI Approved :: GNU General Public License v3 (GPLv3)
Classifier: Operating System :: OS Independent
Classifier: Typing :: Typed
Classifier: Programming Language :: Python
Classifier: Programming Language :: Python :: 3
Classifier: Programming Language :: Python :: 3 :: Only
Classifier: Programming Language :: Python :: 3.8
Classifier: Programming Language :: Python :: 3.9
Classifier: Programming Language :: Python :: 3.10
Classifier: Programming Language :: Python :: 3.11
Requires-Python: >=3.8
Requires-Dist: setuptools
